opt_flow/__init__.py
opt_flow/acceptance/__init__.py
opt_flow/acceptance/all_acceptance.py
opt_flow/acceptance/deterministic_acceptance.py
opt_flow/acceptance/lexicographic_acceptance.py
opt_flow/acceptance/random_acceptance.py
opt_flow/acceptance/scalar_acceptance.py
opt_flow/acceptance/score_acceptance.py
opt_flow/acceptance/simulated_annealing_acceptance.py
opt_flow/acceptance/single_objective_acceptance.py
opt_flow/acceptance/_base/__init__.py
opt_flow/acceptance/_base/base_acceptance.py
opt_flow/callback/__init__.py
opt_flow/callback/acceptance/__init__.py
opt_flow/callback/acceptance/simulated_annealing_update.py
opt_flow/callback/base/__init__.py
opt_flow/callback/base/callback.py
opt_flow/callback/base/callback_args.py
opt_flow/callback/factories/__init__.py
opt_flow/callback/factories/adaptative_factory_update.py
opt_flow/callback/factories/adaptative_ucb_factory_update.py
opt_flow/callback/factories/multiple_trajectory_factory_reset.py
opt_flow/callback/factories/multiple_trajectory_factory_reset_improve.py
opt_flow/callback/logging/__init__.py
opt_flow/callback/logging/metric_logger.py
opt_flow/callback/logging/objective_logger.py
opt_flow/callback/stopping/__init__.py
opt_flow/callback/stopping/parallel_trajectory_time_stopping_update.py
opt_flow/callback/trajectory/__init__.py
opt_flow/callback/trajectory/parallel_polling_update.py
opt_flow/config/__init__.py
opt_flow/config/config.py
opt_flow/core/__init__.py
opt_flow/core/base_population.py
opt_flow/localsearch/__init__.py
opt_flow/localsearch/_base/__init__.py
opt_flow/localsearch/_base/base_local_search.py
opt_flow/localsearch/core/__init__.py
opt_flow/localsearch/core/local_search.py
opt_flow/localsearch/ejection_chain/__init__.py
opt_flow/localsearch/ejection_chain/ejection_chain.py
opt_flow/localsearch/interfaces/__init__.py
opt_flow/localsearch/interfaces/chain_argument_generator.py
opt_flow/localsearch/interfaces/first_movement_selector.py
opt_flow/localsearch/interfaces/link_checker.py
opt_flow_lib-0.1.4.dist-info/METADATA
opt_flow_lib-0.1.4.dist-info/WHEEL
opt_flow_lib-0.1.4.dist-info/top_level.txt
opt_flow_lib-0.1.4.dist-info/RECORD
